k2_asr_metrics/__init__.py
k2_asr_metrics/metrics.py
k2_asr_metrics-0.1.0.dist-info/METADATA
k2_asr_metrics-0.1.0.dist-info/WHEEL
k2_asr_metrics-0.1.0.dist-info/top_level.txt
k2_asr_metrics-0.1.0.dist-info/RECORD
